gsearchpy/__init__.py
gsearchpy/cli.py
gsearchpy/google.py
gsearchpy-0.1.6.dist-info/licenses/LICENSE
gsearchpy-0.1.6.dist-info/METADATA
gsearchpy-0.1.6.dist-info/WHEEL
gsearchpy-0.1.6.dist-info/entry_points.txt
gsearchpy-0.1.6.dist-info/top_level.txt
gsearchpy-0.1.6.dist-info/RECORD
