Metadata-Version: 2.4
Name: gsearchpy
Version: 0.1.6
Summary: A simple Python package for performing Google searches
Home-page: https://github.com/itsguptaaman/gsearchpy
Author: Aman Gupta
Author-email: itsamangupta365@gmail.com
Classifier: Programming Language :: Python :: 3
Classifier: Operating System :: OS Independent
Requires-Python: >=3.6
License-File: LICENSE
Requires-Dist: seleniumbase
Requires-Dist: user_agent
Requires-Dist: curl_cffi
Requires-Dist: bs4
Requires-Dist: lxml
Dynamic: author
Dynamic: author-email
Dynamic: classifier
Dynamic: description
Dynamic: description-content-type
Dynamic: home-page
Dynamic: license-file
Dynamic: requires-dist
Dynamic: requires-python
Dynamic: summary
